FSM.v
/********* FSM Module **********/
    module FSM (
                   input                           Activate         ,
                   input                           Up_Max           ,
                   input                           Dn_Max           ,
                   input                           clk              ,
                   input                           rst              ,
                   output           reg            UP_M             ,
                   output           reg            DN_M             
    );

    //states 
    localparam [1:0] IDLE               =          2'b00 ;
    localparam [1:0] Mv_Up              =          2'b01 ;
    localparam [1:0] Mv_Dn              =          2'b10 ;

    reg [1:0] current_state        ;            
    reg [1:0] next_state           ;

    always @(posedge clk,negedge rst ) begin
        if ((rst==1'b0)) begin
            current_state <= IDLE       ;
        end else begin
            current_state <= next_state ;
        end   
    end    
    always @(Activate or Up_Max or Dn_Max) begin
        case (current_state)
           IDLE :   begin
               if (Activate==1'b0) begin
                   next_state          = IDLE     ;
                   UP_M                = 1'b0     ;
                   DN_M                = 1'b0     ;
               end else if (Dn_Max==1'b1) begin
                   next_state          = Mv_Up    ;
                   UP_M                = 1'b1     ;
                   DN_M                = 1'b0     ;
               end else if (Up_Max==1'b1) begin
                   next_state          = Mv_Dn    ;
                   DN_M                = 1'b1     ;
                   UP_M                = 1'b0     ;
               end else begin
                   next_state          = IDLE     ;
                   UP_M                = 1'b0     ;
                   DN_M                = 1'b0     ;

               end 
               end
               
                   
               
           Mv_Dn :   begin
               if ((Dn_Max==1'b0) && (Activate==1'b1)) begin
                   next_state          = Mv_Dn    ;
                   DN_M                = 1'b1     ;
                   UP_M                = 1'b0     ;
               end 
               else begin
                   next_state          = IDLE     ;
                   UP_M                = 1'b0     ;
                   DN_M                = 1'b0     ;
                   
               end
               end  
           Mv_Up :   begin
               if ((Up_Max==1'b0) && (Activate==1'b1)) begin
                   next_state          = Mv_Up    ;
                   UP_M                = 1'b1     ;
                   DN_M                = 1'b0     ;
               end else begin
                   next_state          = IDLE     ;
                   UP_M                = 1'b0     ;
                   DN_M                = 1'b0     ;
               end
               end     
            
            default: begin
                next_state             = IDLE     ;
                UP_M                   = 1'b0     ;
                DN_M                   = 1'b0     ;
            end
        endcase
    end        
    endmodule

FSM_tb.v
    /*************test bench ***********/
    `timescale 1ns/1ns
    module FSM_tb (
    );
        reg              Activate_tb              ;
        reg              Up_Max_tb                ;
        reg              Dn_Max_tb                ;
        reg              clk_tb                   ;
        reg              rst_tb                   ;
        wire             UP_M_tb                  ;
        wire             DN_M_tb                  ;

        parameter CLOCK_PERIOD = 20               ;
        parameter HALF_PERIOD  = CLOCK_PERIOD / 2 ;
        
        wire [1:0] output_signals                  ;
        assign  output_signals = {DN_M_tb,UP_M_tb} ;
        initial begin
        $dumpfile("FSM.vcd");
        $dumpvars;
        
        clk_tb         = 1'b0                                 ;
        rst_tb         = 1'b0                                 ;
        Activate_tb    = 1'b0                                 ;
        #5
        /******test case 1 ********/
        #3 
        Activate_tb = 1'b1 ;
        Dn_Max_tb   = 1'b0 ;
        Up_Max_tb   = 1'b1 ;
        rst_tb      = 1'b1 ;
        #CLOCK_PERIOD
        //input_signals = 3'b110 ;
        if (output_signals == 2'b10) begin
            $display("test 1 passed");
        end else begin
            $display("test 1 failed");
        end
        /******test case 2 ********/
        
        Activate_tb = 1'b1 ;
        Dn_Max_tb   = 1'b1 ;
        Up_Max_tb   = 1'b0 ;
        rst_tb      = 1'b1 ;
        #CLOCK_PERIOD
        if (output_signals == 2'b00) begin
            $display("test 2 passed");
        end else begin
            $display("test 2 failed");
        end
        /******test case 3 ********/
        Activate_tb = 1'b1 ;
        Dn_Max_tb   = 1'b0 ;
        Up_Max_tb   = 1'b1 ;
        rst_tb      = 1'b1 ;
        #CLOCK_PERIOD
        if (output_signals == 2'b10) begin
            $display("test 3 passed");
        end else begin
            $display("test 3 failed");
        end
        /******test case 4 ********/
        Activate_tb = 1'b0 ;
        Dn_Max_tb   = 1'b0 ;
        Up_Max_tb   = 1'b1 ;
        rst_tb      = 1'b1 ; 
        #CLOCK_PERIOD
        if (output_signals == 2'b00) begin
            $display("test 4 passed");
        end else begin
            $display("test 4 failed");
        end
        /******test case 5 ********/
        Activate_tb = 1'b1 ;
        Dn_Max_tb   = 1'b1 ;
        Up_Max_tb   = 1'b0 ;
        rst_tb      = 1'b1 ; 
        #CLOCK_PERIOD
        if (output_signals == 2'b01) begin
            $display("test 5 passed");
        end else begin
            $display("test 5 failed");
        end
        #1000
        $finish;
        end


    //clock generator
    always #HALF_PERIOD clk_tb = ~ clk_tb     ;

        FSM DUT (
            .Activate(Activate_tb),
            .Up_Max(Up_Max_tb),
            .Dn_Max(Dn_Max_tb),
            .clk(clk_tb),
            .rst(rst_tb),
            .UP_M(UP_M_tb),
            .DN_M(DN_M_tb)
        );
    endmodule

FSM.vcd
$date
	Thu Mar 17 19:04:21 2022
$end
$version
	ModelSim Version 10.5b
$end
$timescale
	1ns
$end

$scope module FSM_tb $end
$var parameter 32 ! CLOCK_PERIOD $end
$var parameter 32 " HALF_PERIOD $end
$var reg 1 # Activate_tb $end
$var reg 1 $ Up_Max_tb $end
$var reg 1 % Dn_Max_tb $end
$var reg 1 & clk_tb $end
$var reg 1 ' rst_tb $end
$var wire 1 ( UP_M_tb $end
$var wire 1 ) DN_M_tb $end
$var wire 1 * output_signals [1] $end
$var wire 1 + output_signals [0] $end

$scope module DUT $end
$var parameter 2 , IDLE $end
$var parameter 2 - Mv_Up $end
$var parameter 2 . Mv_Dn $end
$var wire 1 / Activate $end
$var wire 1 0 Up_Max $end
$var wire 1 1 Dn_Max $end
$var wire 1 2 clk $end
$var wire 1 3 rst $end
$var reg 1 4 UP_M $end
$var reg 1 5 DN_M $end
$var reg 2 6 current_state [1:0] $end
$var reg 2 7 next_state [1:0] $end
$upscope $end
$upscope $end
$enddefinitions $end
#0
$dumpvars
0#
x$
x%
0&
0'
04
05
b0 6
b0 7
b10100 !
b1010 "
b0 ,
b1 -
b10 .
0(
0)
0+
0*
03
02
x1
x0
0/
$end
#8
1#
0%
1$
1'
1/
01
10
13
b10 7
15
1)
1*
#10
1&
12
b10 6
#20
0&
02
#28
1%
0$
11
00
b0 7
05
0)
0*
#30
1&
12
b0 6
#40
0&
02
#48
0%
1$
01
10
b10 7
15
1)
1*
#50
1&
12
b10 6
#60
0&
02
#68
0#
0/
b0 7
05
0)
0*
#70
1&
12
b0 6
#80
0&
02
#88
1#
1%
0$
1/
11
00
b1 7
14
1(
1+
#90
1&
12
b1 6
